.gitattributes
AUTHORS.rst
CHANGES.rst
LICENSE.txt
MANIFEST.in
README.rst
requirements.txt
setup.cfg
setup.py
test-requirements.txt
versioneer.py
dist/virlsdk-0.1.post0.dev2+ng514b6f0.dirty.tar.gz
dist/virlsdk-0.2+ng514b6f0.dirty.tar.gz
dist/virlsdk-0.3+ng3d3b7ef.dirty.tar.gz
dist/virlsdk-0.4+ng0ded3da.dirty.tar.gz
docs/Makefile
docs/authors.rst
docs/changes.rst
docs/conf.py
docs/index.rst
docs/license.rst
docs/virlsdk.rst
docs/_build/doctrees/authors.doctree
docs/_build/doctrees/changes.doctree
docs/_build/doctrees/environment.pickle
docs/_build/doctrees/index.doctree
docs/_build/doctrees/license.doctree
docs/_build/doctrees/virlsdk.doctree
docs/_build/doctrees/api/modules.doctree
docs/_build/doctrees/api/virlsdk.doctree
docs/_build/html/.buildinfo
docs/_build/html/authors.html
docs/_build/html/changes.html
docs/_build/html/genindex.html
docs/_build/html/index.html
docs/_build/html/license.html
docs/_build/html/objects.inv
docs/_build/html/py-modindex.html
docs/_build/html/search.html
docs/_build/html/searchindex.js
docs/_build/html/virlsdk.html
docs/_build/html/_modules/index.html
docs/_build/html/_modules/virlsdk/launch_sim.html
docs/_build/html/_modules/virlsdk/stop_sim.html
docs/_build/html/_modules/virlsdk/virlsdk.html
docs/_build/html/_sources/authors.rst.txt
docs/_build/html/_sources/changes.rst.txt
docs/_build/html/_sources/index.rst.txt
docs/_build/html/_sources/license.rst.txt
docs/_build/html/_sources/virlsdk.rst.txt
docs/_build/html/_sources/api/modules.rst.txt
docs/_build/html/_sources/api/virlsdk.rst.txt
docs/_build/html/_static/ajax-loader.gif
docs/_build/html/_static/alabaster.css
docs/_build/html/_static/basic.css
docs/_build/html/_static/comment-bright.png
docs/_build/html/_static/comment-close.png
docs/_build/html/_static/comment.png
docs/_build/html/_static/custom.css
docs/_build/html/_static/doctools.js
docs/_build/html/_static/down-pressed.png
docs/_build/html/_static/down.png
docs/_build/html/_static/file.png
virlsdk.egg-info/PKG-INFO
virlsdk.egg-info/SOURCES.txt
virlsdk.egg-info/dependency_links.txt
virlsdk.egg-info/not-zip-safe
virlsdk.egg-info/requires.txt
virlsdk.egg-info/top_level.txt