Metadata-Version: 1.1
Name: virlsdk
Version: 0.5
Summary: A python SDK for cisco VIRL APIs
Home-page: http://termlen0.github.io
Author: Ajay Chenampara
Author-email: ajay.chenampara@ge.com
License: mit
Platform: UNKNOWN
Classifier: Development Status :: 4 - Beta
Classifier: Programming Language :: Python
